[
  {
      "name": "crazydave",
      "id": "320161",
      "lvl": "32",
      "total": "990",
      "str": "234",
      "def": "244",
      "spd": "257",
      "dex": "255"
  },
  {
      "name": "maverick1972",
      "id": "522960",
      "lvl": "31",
      "total": "396",
      "str": "106",
      "def": "107",
      "spd": "99",
      "dex": "84"
  },
  {
      "name": "Mataifa",
      "id": "488552",
      "lvl": "31",
      "total": "640",
      "str": "292",
      "def": "39",
      "spd": "218",
      "dex": "91"
  },
  {
      "name": "fanpi017",
      "id": "810355",
      "lvl": "30",
      "total": "654",
      "str": "195",
      "def": "138",
      "spd": "146",
      "dex": "175"
  },
  {
      "name": "Luciii",
      "id": "524912",
      "lvl": "28",
      "total": "579",
      "str": "117",
      "def": "100",
      "spd": "262",
      "dex": "100"
  },
  {
      "name": "-----Nick----",
      "id": "1682111",
      "lvl": "28",
      "total": "638",
      "str": "197",
      "def": "121",
      "spd": "177",
      "dex": "143"
  },
  {
      "name": "russellkill",
      "id": "387822",
      "lvl": "28",
      "total": "763",
      "str": "437",
      "def": "42",
      "spd": "159",
      "dex": "125"
  },
  {
      "name": "themastercheif",
      "id": "566484",
      "lvl": "27",
      "total": "119",
      "str": "38",
      "def": "35",
      "spd": "32",
      "dex": "14"
  },
  {
      "name": "matt007",
      "id": "298167",
      "lvl": "27",
      "total": "194",
      "str": "113",
      "def": "18",
      "spd": "32",
      "dex": "31"
  },
  {
      "name": "babymolly",
      "id": "879148",
      "lvl": "27",
      "total": "227",
      "str": "94",
      "def": "27",
      "spd": "35",
      "dex": "71"
  },
  {
      "name": "Dragon_Reborn",
      "id": "234429",
      "lvl": "27",
      "total": "470",
      "str": "117",
      "def": "69",
      "spd": "173",
      "dex": "111"
  },
  {
      "name": "Sachmo",
      "id": "428732",
      "lvl": "27",
      "total": "580",
      "str": "289",
      "def": "86",
      "spd": "114",
      "dex": "91"
  },
  {
      "name": "tapper85",
      "id": "18798",
      "lvl": "27",
      "total": "582",
      "str": "305",
      "def": "179",
      "spd": "47",
      "dex": "51"
  },
  {
      "name": "james2503",
      "id": "476620",
      "lvl": "26",
      "total": "129",
      "str": "68",
      "def": "11",
      "spd": "34",
      "dex": "16"
  },
  {
      "name": "iBennett",
      "id": "472351",
      "lvl": "26",
      "total": "131",
      "str": "31",
      "def": "54",
      "spd": "21",
      "dex": "25"
  },
  {
      "name": "wilash",
      "id": "807823",
      "lvl": "26",
      "total": "134",
      "str": "65",
      "def": "14",
      "spd": "31",
      "dex": "24"
  },
  {
      "name": "nathwin",
      "id": "1379450",
      "lvl": "26",
      "total": "249",
      "str": "60",
      "def": "62",
      "spd": "66",
      "dex": "61"
  },
  {
      "name": "raysil",
      "id": "796316",
      "lvl": "26",
      "total": "314",
      "str": "158",
      "def": "13",
      "spd": "116",
      "dex": "27"
  },
  {
      "name": "ilekilluall8",
      "id": "316768",
      "lvl": "26",
      "total": "335",
      "str": "139",
      "def": "33",
      "spd": "130",
      "dex": "33"
  },
  {
      "name": "soldierx",
      "id": "153910",
      "lvl": "26",
      "total": "350",
      "str": "97",
      "def": "56",
      "spd": "140",
      "dex": "57"
  },
  {
      "name": "DevilsBlood",
      "id": "76096",
      "lvl": "26",
      "total": "371",
      "str": "240",
      "def": "57",
      "spd": "29",
      "dex": "45"
  },
  {
      "name": "mikeycallin1",
      "id": "659852",
      "lvl": "26",
      "total": "415",
      "str": "128",
      "def": "82",
      "spd": "118",
      "dex": "87"
  },
  {
      "name": "HiredAssasin",
      "id": "450465",
      "lvl": "26",
      "total": "433",
      "str": "316",
      "def": "10",
      "spd": "84",
      "dex": "23"
  },
  {
      "name": "warriorscode",
      "id": "738073",
      "lvl": "26",
      "total": "445",
      "str": "112",
      "def": "141",
      "spd": "114",
      "dex": "78"
  },
  {
      "name": "whiteshadow",
      "id": "284536",
      "lvl": "26",
      "total": "509",
      "str": "135",
      "def": "114",
      "spd": "142",
      "dex": "118"
  },
  {
      "name": "halfblood93",
      "id": "263120",
      "lvl": "26",
      "total": "805",
      "str": "206",
      "def": "123",
      "spd": "371",
      "dex": "105"
  },
  {
      "name": "fortunecookie",
      "id": "729174",
      "lvl": "26",
      "total": "897",
      "str": "305",
      "def": "199",
      "spd": "186",
      "dex": "207"
  },
  {
      "name": "miz_b_haven",
      "id": "251566",
      "lvl": "25",
      "total": "181",
      "str": "69",
      "def": "46",
      "spd": "50",
      "dex": "16"
  },
  {
      "name": "uber44",
      "id": "519062",
      "lvl": "25",
      "total": "205",
      "str": "43",
      "def": "19",
      "spd": "101",
      "dex": "42"
  },
  {
      "name": "Aceraven",
      "id": "1489357",
      "lvl": "25",
      "total": "221",
      "str": "60",
      "def": "61",
      "spd": "55",
      "dex": "45"
  },
  {
      "name": "Boylinger",
      "id": "669996",
      "lvl": "25",
      "total": "264",
      "str": "95",
      "def": "42",
      "spd": "78",
      "dex": "49"
  },
  {
      "name": "nemesis2000",
      "id": "191060",
      "lvl": "25",
      "total": "294",
      "str": "143",
      "def": "29",
      "spd": "90",
      "dex": "32"
  },
  {
      "name": "heva07",
      "id": "454302",
      "lvl": "25",
      "total": "333",
      "str": "50",
      "def": "136",
      "spd": "35",
      "dex": "112"
  },
  {
      "name": "OwlByNite",
      "id": "1046495",
      "lvl": "25",
      "total": "417",
      "str": "124",
      "def": "104",
      "spd": "101",
      "dex": "88"
  },
  {
      "name": "Bob_the_butler",
      "id": "1199189",
      "lvl": "25",
      "total": "423",
      "str": "100",
      "def": "101",
      "spd": "110",
      "dex": "112"
  },
  {
      "name": "ckirklin",
      "id": "485156",
      "lvl": "25",
      "total": "453",
      "str": "195",
      "def": "76",
      "spd": "111",
      "dex": "71"
  },
  {
      "name": "theking99218",
      "id": "1399310",
      "lvl": "25",
      "total": "468",
      "str": "96",
      "def": "164",
      "spd": "95",
      "dex": "113"
  },
  {
      "name": "srfshannon",
      "id": "581300",
      "lvl": "25",
      "total": "475",
      "str": "119",
      "def": "118",
      "spd": "119",
      "dex": "119"
  },
  {
      "name": "RavagedFlamingo",
      "id": "982173",
      "lvl": "25",
      "total": "520",
      "str": "267",
      "def": "121",
      "spd": "96",
      "dex": "36"
  },
  {
      "name": "andre_xavier",
      "id": "211286",
      "lvl": "25",
      "total": "561",
      "str": "199",
      "def": "149",
      "spd": "109",
      "dex": "104"
  },
  {
      "name": "CasterZ",
      "id": "469582",
      "lvl": "25",
      "total": "622",
      "str": "123",
      "def": "77",
      "spd": "228",
      "dex": "194"
  },
  {
      "name": "-Diablo-",
      "id": "652354",
      "lvl": "25",
      "total": "640",
      "str": "213",
      "def": "107",
      "spd": "199",
      "dex": "121"
  },
  {
      "name": "xZULUx",
      "id": "781161",
      "lvl": "25",
      "total": "648",
      "str": "152",
      "def": "147",
      "spd": "198",
      "dex": "151"
  },
  {
      "name": "indo",
      "id": "491724",
      "lvl": "25",
      "total": "716",
      "str": "285",
      "def": "60",
      "spd": "144",
      "dex": "227"
  },
  {
      "name": "kracker65",
      "id": "233040",
      "lvl": "25",
      "total": "719",
      "str": "299",
      "def": "37",
      "spd": "131",
      "dex": "252"
  },
  {
      "name": "Ahad",
      "id": "471136",
      "lvl": "25",
      "total": "738",
      "str": "291",
      "def": "159",
      "spd": "152",
      "dex": "136"
  },
  {
      "name": "terrence_taylor",
      "id": "688148",
      "lvl": "25",
      "total": "824",
      "str": "347",
      "def": "109",
      "spd": "204",
      "dex": "164"
  },
  {
      "name": "Man-u-4-Life",
      "id": "442427",
      "lvl": "25",
      "total": "846",
      "str": "439",
      "def": "27",
      "spd": "366",
      "dex": "14"
  },
  {
      "name": "Morphine2man",
      "id": "588113",
      "lvl": "25",
      "total": "916",
      "str": "364",
      "def": "165",
      "spd": "215",
      "dex": "172"
  },
  {
      "name": "PRlNCE",
      "id": "669588",
      "lvl": "25",
      "total": "970",
      "str": "56",
      "def": "10",
      "spd": "293",
      "dex": "611"
  }
]